adafruit_circuitpython_si7021-4.1.17.dist-info/licenses/LICENSE
adafruit_si7021/__init__.py
adafruit_si7021/i2c_bits.py
adafruit_circuitpython_si7021-4.1.17.dist-info/METADATA
adafruit_circuitpython_si7021-4.1.17.dist-info/WHEEL
adafruit_circuitpython_si7021-4.1.17.dist-info/top_level.txt
adafruit_circuitpython_si7021-4.1.17.dist-info/RECORD
